zspider/__init__.py
zspider/db_handler.py
zspider/dup_filter.py
zspider/except_retry.py
zspider/get_config.py
zspider/httpreq.py
zspider/logger.py
zspider/proxy_base.py
zspider/public_constant.py
zspider/random_headers.py
zspider/seed.py
zspider/seed_handler.py
zspider/simplelib.py
zspider/spider_base.py
zspider-1.0.2.dist-info/LICENSE
zspider-1.0.2.dist-info/METADATA
zspider-1.0.2.dist-info/WHEEL
zspider-1.0.2.dist-info/top_level.txt
zspider-1.0.2.dist-info/RECORD
