Metadata-Version: 2.1
Name: zspider
Version: 1.0.2
Summary: 分布式爬虫精简框架
Home-page: https://pypi.org/project/zspider/
Author: zlyuan
Author-email: 1277260932@qq.com
License: GNU GENERAL PUBLIC LICENSE
Platform: all
Classifier: Environment :: Web Environment
Classifier: Intended Audience :: Developers
Classifier: Operating System :: OS Independent
Classifier: Programming Language :: Python :: 3
Requires-Dist: zssdb (>=0.1.1)
Requires-Dist: zsingleton
Requires-Dist: zretry (>=0.1.1)
Requires-Dist: zinifile (>=1.0.4)
Requires-Dist: requests
Requires-Dist: zlogger (>=0.1.1)
Requires-Dist: zconst
Requires-Dist: lxml
Requires-Dist: msgpack (>=0.6.1)
